pycsv2sqlite/__init__.py
pycsv2sqlite/__main__.py
pycsv2sqlite/main.py
pycsv2sqlite-0.1.0.dist-info/METADATA
pycsv2sqlite-0.1.0.dist-info/WHEEL
pycsv2sqlite-0.1.0.dist-info/entry_points.txt
pycsv2sqlite-0.1.0.dist-info/top_level.txt
pycsv2sqlite-0.1.0.dist-info/RECORD
