Metadata-Version: 2.4
Name: pycsv2sqlite
Version: 0.1.0
Summary: read csv/tsv like file/files and produce sqlite3 db file
Project-URL: Homepage, https://github.com/fxyzbtc/pycsv2sqlite
Project-URL: Issues, https://github.com/fxyzbtc/pycsv2sqlite/issues
Requires-Python: >=3.12
Requires-Dist: pandas>=2.2.3
Requires-Dist: pytest>=8.3.5
Requires-Dist: typer>=0.15.2
Provides-Extra: dev
Requires-Dist: pytest>=8.3.5; extra == "dev"
Requires-Dist: loguru>=0.7.3; extra == "dev"
Requires-Dist: pytest-cov>=4.1.0; extra == "dev"
Requires-Dist: black>=24.2.0; extra == "dev"
Requires-Dist: isort>=5.13.2; extra == "dev"
